{
  "as_of": "2026-03-08T04:17:02.477Z",
  "provider": "mock_generator",
  "market_session": "after_hours",
  "items": [
    {
      "symbol": "ASTS",
      "price_usd": 89.47,
      "price_type": "close",
      "market_state": "closed",
      "is_delayed": true,
      "stale_level": "fresh",
      "error": null,
      "change_percent": -4.67,
      "change_amount": -4.39,
      "volume": 13555000,
      "close_price": 89.47,
      "after_hours_price": null,
      "after_hours_change_percent": null,
      "after_hours_change_amount": null
    },
    {
      "symbol": "RIVN",
      "price_usd": 15.37,
      "price_type": "close",
      "market_state": "closed",
      "is_delayed": true,
      "stale_level": "fresh",
      "error": null,
      "change_percent": 1.18,
      "change_amount": 0.18,
      "volume": 24847800,
      "close_price": 15.37,
      "after_hours_price": null,
      "after_hours_change_percent": null,
      "after_hours_change_amount": null
    },
    {
      "symbol": "PL",
      "price_usd": 25.28,
      "price_type": "close",
      "market_state": "closed",
      "is_delayed": true,
      "stale_level": "fresh",
      "error": null,
      "change_percent": 2.81,
      "change_amount": 0.69,
      "volume": 14088100,
      "close_price": 25.28,
      "after_hours_price": null,
      "after_hours_change_percent": null,
      "after_hours_change_amount": null
    },
    {
      "symbol": "ONDS",
      "price_usd": 9.83,
      "price_type": "close",
      "market_state": "closed",
      "is_delayed": true,
      "stale_level": "fresh",
      "error": null,
      "change_percent": -6.29,
      "change_amount": -0.66,
      "volume": 159845600,
      "close_price": 9.83,
      "after_hours_price": null,
      "after_hours_change_percent": null,
      "after_hours_change_amount": null
    },
    {
      "symbol": "RDW",
      "price_usd": 8.55,
      "price_type": "close",
      "market_state": "closed",
      "is_delayed": true,
      "stale_level": "fresh",
      "error": null,
      "change_percent": -5.73,
      "change_amount": -0.52,
      "volume": 17775800,
      "close_price": 8.55,
      "after_hours_price": null,
      "after_hours_change_percent": null,
      "after_hours_change_amount": null
    },
    {
      "symbol": "AVAV",
      "price_usd": 229.8,
      "price_type": "close",
      "market_state": "closed",
      "is_delayed": true,
      "stale_level": "fresh",
      "error": null,
      "change_percent": 4.19,
      "change_amount": 9.24,
      "volume": 2115300,
      "close_price": 229.8,
      "after_hours_price": null,
      "after_hours_change_percent": null,
      "after_hours_change_amount": null
    },
    {
      "symbol": "MDB",
      "price_usd": 270.47,
      "price_type": "close",
      "market_state": "closed",
      "is_delayed": true,
      "stale_level": "fresh",
      "error": null,
      "change_percent": 2.48,
      "change_amount": 6.54,
      "volume": 2995400,
      "close_price": 270.47,
      "after_hours_price": null,
      "after_hours_change_percent": null,
      "after_hours_change_amount": null
    },
    {
      "symbol": "ORCL",
      "price_usd": 152.96,
      "price_type": "close",
      "market_state": "closed",
      "is_delayed": true,
      "stale_level": "fresh",
      "error": null,
      "change_percent": -1.18,
      "change_amount": -1.83,
      "volume": 37916400,
      "close_price": 152.96,
      "after_hours_price": null,
      "after_hours_change_percent": null,
      "after_hours_change_amount": null
    },
    {
      "symbol": "TSM",
      "price_usd": 338.89,
      "price_type": "close",
      "market_state": "closed",
      "is_delayed": true,
      "stale_level": "fresh",
      "error": null,
      "change_percent": -4.23,
      "change_amount": -14.97,
      "volume": 13758500,
      "close_price": 338.89,
      "after_hours_price": null,
      "after_hours_change_percent": null,
      "after_hours_change_amount": null
    },
    {
      "symbol": "RKLB",
      "price_usd": 70.11,
      "price_type": "close",
      "market_state": "closed",
      "is_delayed": true,
      "stale_level": "fresh",
      "error": null,
      "change_percent": 0.16,
      "change_amount": 0.11,
      "volume": 22185400,
      "close_price": 70.11,
      "after_hours_price": null,
      "after_hours_change_percent": null,
      "after_hours_change_amount": null
    },
    {
      "symbol": "CRM",
      "price_usd": 202.11,
      "price_type": "close",
      "market_state": "closed",
      "is_delayed": true,
      "stale_level": "fresh",
      "error": null,
      "change_percent": 0.36,
      "change_amount": 0.72,
      "volume": 9653200,
      "close_price": 202.11,
      "after_hours_price": null,
      "after_hours_change_percent": null,
      "after_hours_change_amount": null
    },
    {
      "symbol": "NVDA",
      "price_usd": 177.82,
      "price_type": "close",
      "market_state": "closed",
      "is_delayed": true,
      "stale_level": "fresh",
      "error": null,
      "change_percent": -3.01,
      "change_amount": -5.52,
      "volume": 188472400,
      "close_price": 177.82,
      "after_hours_price": null,
      "after_hours_change_percent": null,
      "after_hours_change_amount": null
    },
    {
      "symbol": "AVGO",
      "price_usd": 330.48,
      "price_type": "close",
      "market_state": "closed",
      "is_delayed": true,
      "stale_level": "fresh",
      "error": null,
      "change_percent": -0.69,
      "change_amount": -2.29,
      "volume": 39103700,
      "close_price": 330.48,
      "after_hours_price": null,
      "after_hours_change_percent": null,
      "after_hours_change_amount": null
    },
    {
      "symbol": "AMZN",
      "price_usd": 213.21,
      "price_type": "close",
      "market_state": "closed",
      "is_delayed": true,
      "stale_level": "fresh",
      "error": null,
      "change_percent": -2.62,
      "change_amount": -5.73,
      "volume": 51090300,
      "close_price": 213.21,
      "after_hours_price": null,
      "after_hours_change_percent": null,
      "after_hours_change_amount": null
    },
    {
      "symbol": "GOOG",
      "price_usd": 298.3,
      "price_type": "close",
      "market_state": "closed",
      "is_delayed": true,
      "stale_level": "fresh",
      "error": null,
      "change_percent": -0.87,
      "change_amount": -2.61,
      "volume": 17574900,
      "close_price": 298.3,
      "after_hours_price": null,
      "after_hours_change_percent": null,
      "after_hours_change_amount": null
    },
    {
      "symbol": "META",
      "price_usd": 644.86,
      "price_type": "close",
      "market_state": "closed",
      "is_delayed": true,
      "stale_level": "fresh",
      "error": null,
      "change_percent": -2.38,
      "change_amount": -15.71,
      "volume": 13128500,
      "close_price": 644.86,
      "after_hours_price": null,
      "after_hours_change_percent": null,
      "after_hours_change_amount": null
    },
    {
      "symbol": "NFLX",
      "price_usd": 99.02,
      "price_type": "close",
      "market_state": "closed",
      "is_delayed": true,
      "stale_level": "fresh",
      "error": null,
      "change_percent": -0.15,
      "change_amount": -0.15,
      "volume": 41111100,
      "close_price": 99.02,
      "after_hours_price": null,
      "after_hours_change_percent": null,
      "after_hours_change_amount": null
    },
    {
      "symbol": "LEU",
      "price_usd": 188.89,
      "price_type": "close",
      "market_state": "closed",
      "is_delayed": true,
      "stale_level": "fresh",
      "error": null,
      "change_percent": -2.77,
      "change_amount": -5.39,
      "volume": 962100,
      "close_price": 188.89,
      "after_hours_price": null,
      "after_hours_change_percent": null,
      "after_hours_change_amount": null
    },
    {
      "symbol": "SMR",
      "price_usd": 11.67,
      "price_type": "close",
      "market_state": "closed",
      "is_delayed": true,
      "stale_level": "fresh",
      "error": null,
      "change_percent": -4.19,
      "change_amount": -0.51,
      "volume": 25099500,
      "close_price": 11.67,
      "after_hours_price": null,
      "after_hours_change_percent": null,
      "after_hours_change_amount": null
    },
    {
      "symbol": "CRWV",
      "price_usd": 72.99,
      "price_type": "close",
      "market_state": "closed",
      "is_delayed": true,
      "stale_level": "fresh",
      "error": null,
      "change_percent": -2.45,
      "change_amount": -1.83,
      "volume": 25495400,
      "close_price": 72.99,
      "after_hours_price": null,
      "after_hours_change_percent": null,
      "after_hours_change_amount": null
    },
    {
      "symbol": "IONQ",
      "price_usd": 35.73,
      "price_type": "close",
      "market_state": "closed",
      "is_delayed": true,
      "stale_level": "fresh",
      "error": null,
      "change_percent": -0.81,
      "change_amount": -0.29,
      "volume": 18431700,
      "close_price": 35.73,
      "after_hours_price": null,
      "after_hours_change_percent": null,
      "after_hours_change_amount": null
    },
    {
      "symbol": "PLTR",
      "price_usd": 157.16,
      "price_type": "close",
      "market_state": "closed",
      "is_delayed": true,
      "stale_level": "fresh",
      "error": null,
      "change_percent": 2.94,
      "change_amount": 4.49,
      "volume": 74824200,
      "close_price": 157.16,
      "after_hours_price": null,
      "after_hours_change_percent": null,
      "after_hours_change_amount": null
    },
    {
      "symbol": "HIMS",
      "price_usd": 15.74,
      "price_type": "close",
      "market_state": "closed",
      "is_delayed": true,
      "stale_level": "fresh",
      "error": null,
      "change_percent": -0.88,
      "change_amount": -0.14,
      "volume": 14466800,
      "close_price": 15.74,
      "after_hours_price": null,
      "after_hours_change_percent": null,
      "after_hours_change_amount": null
    },
    {
      "symbol": "TSLA",
      "price_usd": 396.73,
      "price_type": "close",
      "market_state": "closed",
      "is_delayed": true,
      "stale_level": "fresh",
      "error": null,
      "change_percent": -2.17,
      "change_amount": -8.82,
      "volume": 63870200,
      "close_price": 396.73,
      "after_hours_price": null,
      "after_hours_change_percent": null,
      "after_hours_change_amount": null
    },
    {
      "symbol": "VST",
      "price_usd": 158.65,
      "price_type": "close",
      "market_state": "closed",
      "is_delayed": true,
      "stale_level": "fresh",
      "error": null,
      "change_percent": -5.23,
      "change_amount": -8.75,
      "volume": 5616400,
      "close_price": 158.65,
      "after_hours_price": null,
      "after_hours_change_percent": null,
      "after_hours_change_amount": null
    },
    {
      "symbol": "KTOS",
      "price_usd": 87,
      "price_type": "close",
      "market_state": "closed",
      "is_delayed": true,
      "stale_level": "fresh",
      "error": null,
      "change_percent": 1.71,
      "change_amount": 1.46,
      "volume": 5376500,
      "close_price": 87,
      "after_hours_price": null,
      "after_hours_change_percent": null,
      "after_hours_change_amount": null
    },
    {
      "symbol": "MELI",
      "price_usd": 1787.86,
      "price_type": "close",
      "market_state": "closed",
      "is_delayed": true,
      "stale_level": "fresh",
      "error": null,
      "change_percent": 0.42,
      "change_amount": 7.5,
      "volume": 439900,
      "close_price": 1787.86,
      "after_hours_price": null,
      "after_hours_change_percent": null,
      "after_hours_change_amount": null
    },
    {
      "symbol": "SOFI",
      "price_usd": 18.9,
      "price_type": "close",
      "market_state": "closed",
      "is_delayed": true,
      "stale_level": "fresh",
      "error": null,
      "change_percent": -1.82,
      "change_amount": -0.35,
      "volume": 75885800,
      "close_price": 18.9,
      "after_hours_price": null,
      "after_hours_change_percent": null,
      "after_hours_change_amount": null
    },
    {
      "symbol": "RBRK",
      "price_usd": 57.17,
      "price_type": "close",
      "market_state": "closed",
      "is_delayed": true,
      "stale_level": "fresh",
      "error": null,
      "change_percent": 2.31,
      "change_amount": 1.29,
      "volume": 3445500,
      "close_price": 57.17,
      "after_hours_price": null,
      "after_hours_change_percent": null,
      "after_hours_change_amount": null
    },
    {
      "symbol": "EOSE",
      "price_usd": 6.13,
      "price_type": "close",
      "market_state": "closed",
      "is_delayed": true,
      "stale_level": "fresh",
      "error": null,
      "change_percent": -8.78,
      "change_amount": -0.59,
      "volume": 19677000,
      "close_price": 6.13,
      "after_hours_price": null,
      "after_hours_change_percent": null,
      "after_hours_change_amount": null
    },
    {
      "symbol": "CEG",
      "price_usd": 319.06,
      "price_type": "close",
      "market_state": "closed",
      "is_delayed": true,
      "stale_level": "fresh",
      "error": null,
      "change_percent": -3.92,
      "change_amount": -13.01,
      "volume": 3430100,
      "close_price": 319.06,
      "after_hours_price": null,
      "after_hours_change_percent": null,
      "after_hours_change_amount": null
    },
    {
      "symbol": "TMDX",
      "price_usd": 129.61,
      "price_type": "close",
      "market_state": "closed",
      "is_delayed": true,
      "stale_level": "fresh",
      "error": null,
      "change_percent": -7.47,
      "change_amount": -10.46,
      "volume": 1079700,
      "close_price": 129.61,
      "after_hours_price": null,
      "after_hours_change_percent": null,
      "after_hours_change_amount": null
    },
    {
      "symbol": "GRAB",
      "price_usd": 3.98,
      "price_type": "close",
      "market_state": "closed",
      "is_delayed": true,
      "stale_level": "fresh",
      "error": null,
      "change_percent": -1.24,
      "change_amount": -0.05,
      "volume": 34095200,
      "close_price": 3.98,
      "after_hours_price": null,
      "after_hours_change_percent": null,
      "after_hours_change_amount": null
    },
    {
      "symbol": "RBLX",
      "price_usd": 63.53,
      "price_type": "close",
      "market_state": "closed",
      "is_delayed": true,
      "stale_level": "fresh",
      "error": null,
      "change_percent": -3.86,
      "change_amount": -2.55,
      "volume": 8143900,
      "close_price": 63.53,
      "after_hours_price": null,
      "after_hours_change_percent": null,
      "after_hours_change_amount": null
    },
    {
      "symbol": "IREN",
      "price_usd": 36.7,
      "price_type": "close",
      "market_state": "closed",
      "is_delayed": true,
      "stale_level": "fresh",
      "error": null,
      "change_percent": -8.54,
      "change_amount": -3.42,
      "volume": 34493900,
      "close_price": 36.7,
      "after_hours_price": null,
      "after_hours_change_percent": null,
      "after_hours_change_amount": null
    },
    {
      "symbol": "OKLO",
      "price_usd": 58.25,
      "price_type": "close",
      "market_state": "closed",
      "is_delayed": true,
      "stale_level": "fresh",
      "error": null,
      "change_percent": -6.09,
      "change_amount": -3.78,
      "volume": 8795800,
      "close_price": 58.25,
      "after_hours_price": null,
      "after_hours_change_percent": null,
      "after_hours_change_amount": null
    },
    {
      "symbol": "PATH",
      "price_usd": 11.86,
      "price_type": "close",
      "market_state": "closed",
      "is_delayed": true,
      "stale_level": "fresh",
      "error": null,
      "change_percent": 2.68,
      "change_amount": 0.31,
      "volume": 39543800,
      "close_price": 11.86,
      "after_hours_price": null,
      "after_hours_change_percent": null,
      "after_hours_change_amount": null
    },
    {
      "symbol": "INTR",
      "price_usd": 8.02,
      "price_type": "close",
      "market_state": "closed",
      "is_delayed": true,
      "stale_level": "fresh",
      "error": null,
      "change_percent": -2.67,
      "change_amount": -0.22,
      "volume": 2867000,
      "close_price": 8.02,
      "after_hours_price": null,
      "after_hours_change_percent": null,
      "after_hours_change_amount": null
    },
    {
      "symbol": "SE",
      "price_usd": 91.98,
      "price_type": "close",
      "market_state": "closed",
      "is_delayed": true,
      "stale_level": "fresh",
      "error": null,
      "change_percent": -3.71,
      "change_amount": -3.54,
      "volume": 7463900,
      "close_price": 91.98,
      "after_hours_price": null,
      "after_hours_change_percent": null,
      "after_hours_change_amount": null
    },
    {
      "symbol": "KSPI",
      "price_usd": 74.2,
      "price_type": "close",
      "market_state": "closed",
      "is_delayed": true,
      "stale_level": "fresh",
      "error": null,
      "change_percent": -0.59,
      "change_amount": -0.44,
      "volume": 821600,
      "close_price": 74.2,
      "after_hours_price": null,
      "after_hours_change_percent": null,
      "after_hours_change_amount": null
    },
    {
      "symbol": "LUNR",
      "price_usd": 17.63,
      "price_type": "close",
      "market_state": "closed",
      "is_delayed": true,
      "stale_level": "fresh",
      "error": null,
      "change_percent": -0.23,
      "change_amount": -0.04,
      "volume": 11523600,
      "close_price": 17.63,
      "after_hours_price": null,
      "after_hours_change_percent": null,
      "after_hours_change_amount": null
    },
    {
      "symbol": "HOOD",
      "price_usd": 77.09,
      "price_type": "close",
      "market_state": "closed",
      "is_delayed": true,
      "stale_level": "fresh",
      "error": null,
      "change_percent": -4.31,
      "change_amount": -3.47,
      "volume": 28642500,
      "close_price": 77.09,
      "after_hours_price": null,
      "after_hours_change_percent": null,
      "after_hours_change_amount": null
    },
    {
      "symbol": "APP",
      "price_usd": 502.14,
      "price_type": "close",
      "market_state": "closed",
      "is_delayed": true,
      "stale_level": "fresh",
      "error": null,
      "change_percent": -1.26,
      "change_amount": -6.42,
      "volume": 5170700,
      "close_price": 502.14,
      "after_hours_price": null,
      "after_hours_change_percent": null,
      "after_hours_change_amount": null
    },
    {
      "symbol": "CHYM",
      "price_usd": 22.23,
      "price_type": "close",
      "market_state": "closed",
      "is_delayed": true,
      "stale_level": "fresh",
      "error": null,
      "change_percent": -3.81,
      "change_amount": -0.88,
      "volume": 3451800,
      "close_price": 22.23,
      "after_hours_price": null,
      "after_hours_change_percent": null,
      "after_hours_change_amount": null
    },
    {
      "symbol": "NU",
      "price_usd": 14.58,
      "price_type": "close",
      "market_state": "closed",
      "is_delayed": true,
      "stale_level": "fresh",
      "error": null,
      "change_percent": -1.62,
      "change_amount": -0.24,
      "volume": 51933800,
      "close_price": 14.58,
      "after_hours_price": null,
      "after_hours_change_percent": null,
      "after_hours_change_amount": null
    },
    {
      "symbol": "COIN",
      "price_usd": 197.22,
      "price_type": "close",
      "market_state": "closed",
      "is_delayed": true,
      "stale_level": "fresh",
      "error": null,
      "change_percent": -4.13,
      "change_amount": -8.49,
      "volume": 11473000,
      "close_price": 197.22,
      "after_hours_price": null,
      "after_hours_change_percent": null,
      "after_hours_change_amount": null
    },
    {
      "symbol": "CRCL",
      "price_usd": 101.91,
      "price_type": "close",
      "market_state": "closed",
      "is_delayed": true,
      "stale_level": "fresh",
      "error": null,
      "change_percent": -3.62,
      "change_amount": -3.83,
      "volume": 19583700,
      "close_price": 101.91,
      "after_hours_price": null,
      "after_hours_change_percent": null,
      "after_hours_change_amount": null
    },
    {
      "symbol": "IBKR",
      "price_usd": 66.7,
      "price_type": "close",
      "market_state": "closed",
      "is_delayed": true,
      "stale_level": "fresh",
      "error": null,
      "change_percent": -1.98,
      "change_amount": -1.35,
      "volume": 5375000,
      "close_price": 66.7,
      "after_hours_price": null,
      "after_hours_change_percent": null,
      "after_hours_change_amount": null
    },
    {
      "symbol": "CCJ",
      "price_usd": 109.68,
      "price_type": "close",
      "market_state": "closed",
      "is_delayed": true,
      "stale_level": "fresh",
      "error": null,
      "change_percent": -3.99,
      "change_amount": -4.56,
      "volume": 4110500,
      "close_price": 109.68,
      "after_hours_price": null,
      "after_hours_change_percent": null,
      "after_hours_change_amount": null
    },
    {
      "symbol": "UUUU",
      "price_usd": 19.03,
      "price_type": "close",
      "market_state": "closed",
      "is_delayed": true,
      "stale_level": "fresh",
      "error": null,
      "change_percent": -6.35,
      "change_amount": -1.29,
      "volume": 10346200,
      "close_price": 19.03,
      "after_hours_price": null,
      "after_hours_change_percent": null,
      "after_hours_change_amount": null
    },
    {
      "symbol": "VRT",
      "price_usd": 241.78,
      "price_type": "close",
      "market_state": "closed",
      "is_delayed": true,
      "stale_level": "fresh",
      "error": null,
      "change_percent": -3.19,
      "change_amount": -7.97,
      "volume": 8659200,
      "close_price": 241.78,
      "after_hours_price": null,
      "after_hours_change_percent": null,
      "after_hours_change_amount": null
    },
    {
      "symbol": "ETN",
      "price_usd": 347.75,
      "price_type": "close",
      "market_state": "closed",
      "is_delayed": true,
      "stale_level": "fresh",
      "error": null,
      "change_percent": -1.98,
      "change_amount": -7.04,
      "volume": 3794600,
      "close_price": 347.75,
      "after_hours_price": null,
      "after_hours_change_percent": null,
      "after_hours_change_amount": null
    },
    {
      "symbol": "MSFT",
      "price_usd": 408.96,
      "price_type": "close",
      "market_state": "closed",
      "is_delayed": true,
      "stale_level": "fresh",
      "error": null,
      "change_percent": -0.42,
      "change_amount": -1.72,
      "volume": 31085000,
      "close_price": 408.96,
      "after_hours_price": null,
      "after_hours_change_percent": null,
      "after_hours_change_amount": null
    },
    {
      "symbol": "ADBE",
      "price_usd": 283.62,
      "price_type": "close",
      "market_state": "closed",
      "is_delayed": true,
      "stale_level": "fresh",
      "error": null,
      "change_percent": 0.67,
      "change_amount": 1.88,
      "volume": 4797300,
      "close_price": 283.62,
      "after_hours_price": null,
      "after_hours_change_percent": null,
      "after_hours_change_amount": null
    },
    {
      "symbol": "FIG",
      "price_usd": 29.11,
      "price_type": "close",
      "market_state": "closed",
      "is_delayed": true,
      "stale_level": "fresh",
      "error": null,
      "change_percent": -3.93,
      "change_amount": -1.19,
      "volume": 8561500,
      "close_price": 29.11,
      "after_hours_price": null,
      "after_hours_change_percent": null,
      "after_hours_change_amount": null
    },
    {
      "symbol": "PANW",
      "price_usd": 165.05,
      "price_type": "close",
      "market_state": "closed",
      "is_delayed": true,
      "stale_level": "fresh",
      "error": null,
      "change_percent": 1.16,
      "change_amount": 1.89,
      "volume": 7198700,
      "close_price": 165.05,
      "after_hours_price": null,
      "after_hours_change_percent": null,
      "after_hours_change_amount": null
    },
    {
      "symbol": "CRWD",
      "price_usd": 428.99,
      "price_type": "close",
      "market_state": "closed",
      "is_delayed": true,
      "stale_level": "fresh",
      "error": null,
      "change_percent": 0.66,
      "change_amount": 2.83,
      "volume": 4596200,
      "close_price": 428.99,
      "after_hours_price": null,
      "after_hours_change_percent": null,
      "after_hours_change_amount": null
    },
    {
      "symbol": "DDOG",
      "price_usd": 125.75,
      "price_type": "close",
      "market_state": "closed",
      "is_delayed": true,
      "stale_level": "fresh",
      "error": null,
      "change_percent": 2.77,
      "change_amount": 3.39,
      "volume": 4044300,
      "close_price": 125.75,
      "after_hours_price": null,
      "after_hours_change_percent": null,
      "after_hours_change_amount": null
    },
    {
      "symbol": "DUOL",
      "price_usd": 101.92,
      "price_type": "close",
      "market_state": "closed",
      "is_delayed": true,
      "stale_level": "fresh",
      "error": null,
      "change_percent": 0.37,
      "change_amount": 0.38,
      "volume": 2010100,
      "close_price": 101.92,
      "after_hours_price": null,
      "after_hours_change_percent": null,
      "after_hours_change_amount": null
    },
    {
      "symbol": "ZETA",
      "price_usd": 18.84,
      "price_type": "close",
      "market_state": "closed",
      "is_delayed": true,
      "stale_level": "fresh",
      "error": null,
      "change_percent": -0.37,
      "change_amount": -0.07,
      "volume": 6698000,
      "close_price": 18.84,
      "after_hours_price": null,
      "after_hours_change_percent": null,
      "after_hours_change_amount": null
    },
    {
      "symbol": "AXON",
      "price_usd": 574.01,
      "price_type": "close",
      "market_state": "closed",
      "is_delayed": true,
      "stale_level": "fresh",
      "error": null,
      "change_percent": 0.62,
      "change_amount": 3.52,
      "volume": 653400,
      "close_price": 574.01,
      "after_hours_price": null,
      "after_hours_change_percent": null,
      "after_hours_change_amount": null
    },
    {
      "symbol": "ALAB",
      "price_usd": 119.2,
      "price_type": "close",
      "market_state": "closed",
      "is_delayed": true,
      "stale_level": "fresh",
      "error": null,
      "change_percent": -0.67,
      "change_amount": -0.8,
      "volume": 4427400,
      "close_price": 119.2,
      "after_hours_price": null,
      "after_hours_change_percent": null,
      "after_hours_change_amount": null
    },
    {
      "symbol": "LRCX",
      "price_usd": 199.33,
      "price_type": "close",
      "market_state": "closed",
      "is_delayed": true,
      "stale_level": "fresh",
      "error": null,
      "change_percent": -7.15,
      "change_amount": -15.35,
      "volume": 13588900,
      "close_price": 199.33,
      "after_hours_price": null,
      "after_hours_change_percent": null,
      "after_hours_change_amount": null
    },
    {
      "symbol": "BWXT",
      "price_usd": 195.23,
      "price_type": "close",
      "market_state": "closed",
      "is_delayed": true,
      "stale_level": "fresh",
      "error": null,
      "change_percent": -0.14,
      "change_amount": -0.27,
      "volume": 728800,
      "close_price": 195.23,
      "after_hours_price": null,
      "after_hours_change_percent": null,
      "after_hours_change_amount": null
    },
    {
      "symbol": "UMAC",
      "price_usd": 16.45,
      "price_type": "close",
      "market_state": "closed",
      "is_delayed": true,
      "stale_level": "fresh",
      "error": null,
      "change_percent": 7.8,
      "change_amount": 1.19,
      "volume": 7258600,
      "close_price": 16.45,
      "after_hours_price": null,
      "after_hours_change_percent": null,
      "after_hours_change_amount": null
    },
    {
      "symbol": "MP",
      "price_usd": 58.23,
      "price_type": "close",
      "market_state": "closed",
      "is_delayed": true,
      "stale_level": "fresh",
      "error": null,
      "change_percent": -0.43,
      "change_amount": -0.25,
      "volume": 5580200,
      "close_price": 58.23,
      "after_hours_price": null,
      "after_hours_change_percent": null,
      "after_hours_change_amount": null
    },
    {
      "symbol": "RR",
      "price_usd": 2.36,
      "price_type": "close",
      "market_state": "closed",
      "is_delayed": true,
      "stale_level": "fresh",
      "error": null,
      "change_percent": -2.48,
      "change_amount": -0.06,
      "volume": 7375900,
      "close_price": 2.36,
      "after_hours_price": null,
      "after_hours_change_percent": null,
      "after_hours_change_amount": null
    },
    {
      "symbol": "ABBV",
      "price_usd": 230.11,
      "price_type": "close",
      "market_state": "closed",
      "is_delayed": true,
      "stale_level": "fresh",
      "error": null,
      "change_percent": -0.96,
      "change_amount": -2.24,
      "volume": 6139600,
      "close_price": 230.11,
      "after_hours_price": null,
      "after_hours_change_percent": null,
      "after_hours_change_amount": null
    },
    {
      "symbol": "ACHR",
      "price_usd": 6.26,
      "price_type": "close",
      "market_state": "closed",
      "is_delayed": true,
      "stale_level": "fresh",
      "error": null,
      "change_percent": -3.1,
      "change_amount": -0.2,
      "volume": 30826800,
      "close_price": 6.26,
      "after_hours_price": null,
      "after_hours_change_percent": null,
      "after_hours_change_amount": null
    },
    {
      "symbol": "AMD",
      "price_usd": 192.43,
      "price_type": "close",
      "market_state": "closed",
      "is_delayed": true,
      "stale_level": "fresh",
      "error": null,
      "change_percent": -3.52,
      "change_amount": -7.02,
      "volume": 33813900,
      "close_price": 192.43,
      "after_hours_price": null,
      "after_hours_change_percent": null,
      "after_hours_change_amount": null
    },
    {
      "symbol": "AXP",
      "price_usd": 301,
      "price_type": "close",
      "market_state": "closed",
      "is_delayed": true,
      "stale_level": "fresh",
      "error": null,
      "change_percent": -2.02,
      "change_amount": -6.21,
      "volume": 5499300,
      "close_price": 301,
      "after_hours_price": null,
      "after_hours_change_percent": null,
      "after_hours_change_amount": null
    },
    {
      "symbol": "BA",
      "price_usd": 231.11,
      "price_type": "close",
      "market_state": "closed",
      "is_delayed": true,
      "stale_level": "fresh",
      "error": null,
      "change_percent": 4.08,
      "change_amount": 9.05,
      "volume": 10668200,
      "close_price": 231.11,
      "after_hours_price": null,
      "after_hours_change_percent": null,
      "after_hours_change_amount": null
    },
    {
      "symbol": "BAC",
      "price_usd": 48.64,
      "price_type": "close",
      "market_state": "closed",
      "is_delayed": true,
      "stale_level": "fresh",
      "error": null,
      "change_percent": -2.35,
      "change_amount": -1.17,
      "volume": 47001400,
      "close_price": 48.64,
      "after_hours_price": null,
      "after_hours_change_percent": null,
      "after_hours_change_amount": null
    },
    {
      "symbol": "BE",
      "price_usd": 135.19,
      "price_type": "close",
      "market_state": "closed",
      "is_delayed": true,
      "stale_level": "fresh",
      "error": null,
      "change_percent": -15.5,
      "change_amount": -24.8,
      "volume": 14772900,
      "close_price": 135.19,
      "after_hours_price": null,
      "after_hours_change_percent": null,
      "after_hours_change_amount": null
    },
    {
      "symbol": "BRK-B",
      "price_usd": 498.98,
      "price_type": "close",
      "market_state": "closed",
      "is_delayed": true,
      "stale_level": "fresh",
      "error": null,
      "change_percent": -0.28,
      "change_amount": -1.42,
      "volume": 5560000,
      "close_price": 498.98,
      "after_hours_price": null,
      "after_hours_change_percent": null,
      "after_hours_change_amount": null
    },
    {
      "symbol": "CAT",
      "price_usd": 680.9,
      "price_type": "close",
      "market_state": "closed",
      "is_delayed": true,
      "stale_level": "fresh",
      "error": null,
      "change_percent": -3.57,
      "change_amount": -25.18,
      "volume": 3559700,
      "close_price": 680.9,
      "after_hours_price": null,
      "after_hours_change_percent": null,
      "after_hours_change_amount": null
    },
    {
      "symbol": "CIFR",
      "price_usd": 13.62,
      "price_type": "close",
      "market_state": "closed",
      "is_delayed": true,
      "stale_level": "fresh",
      "error": null,
      "change_percent": -10.1,
      "change_amount": -1.53,
      "volume": 27428100,
      "close_price": 13.62,
      "after_hours_price": null,
      "after_hours_change_percent": null,
      "after_hours_change_amount": null
    },
    {
      "symbol": "CLSK",
      "price_usd": 9.21,
      "price_type": "close",
      "market_state": "closed",
      "is_delayed": true,
      "stale_level": "fresh",
      "error": null,
      "change_percent": -7.44,
      "change_amount": -0.74,
      "volume": 16149500,
      "close_price": 9.21,
      "after_hours_price": null,
      "after_hours_change_percent": null,
      "after_hours_change_amount": null
    },
    {
      "symbol": "COST",
      "price_usd": 998.1,
      "price_type": "close",
      "market_state": "closed",
      "is_delayed": true,
      "stale_level": "fresh",
      "error": null,
      "change_percent": 1.58,
      "change_amount": 15.53,
      "volume": 2707200,
      "close_price": 998.1,
      "after_hours_price": null,
      "after_hours_change_percent": null,
      "after_hours_change_amount": null
    },
    {
      "symbol": "CSCO",
      "price_usd": 78.64,
      "price_type": "close",
      "market_state": "closed",
      "is_delayed": true,
      "stale_level": "fresh",
      "error": null,
      "change_percent": -1.71,
      "change_amount": -1.37,
      "volume": 20620400,
      "close_price": 78.64,
      "after_hours_price": null,
      "after_hours_change_percent": null,
      "after_hours_change_amount": null
    },
    {
      "symbol": "CVX",
      "price_usd": 189.94,
      "price_type": "close",
      "market_state": "closed",
      "is_delayed": true,
      "stale_level": "fresh",
      "error": null,
      "change_percent": 0.02,
      "change_amount": 0.04,
      "volume": 13059800,
      "close_price": 189.94,
      "after_hours_price": null,
      "after_hours_change_percent": null,
      "after_hours_change_amount": null
    },
    {
      "symbol": "DGRO",
      "price_usd": 71.65,
      "price_type": "close",
      "market_state": "closed",
      "is_delayed": true,
      "stale_level": "fresh",
      "error": null,
      "change_percent": -0.83,
      "change_amount": -0.6,
      "volume": 3806800,
      "close_price": 71.65,
      "after_hours_price": null,
      "after_hours_change_percent": null,
      "after_hours_change_amount": null
    },
    {
      "symbol": "DIA",
      "price_usd": 475.23,
      "price_type": "close",
      "market_state": "closed",
      "is_delayed": true,
      "stale_level": "fresh",
      "error": null,
      "change_percent": -0.96,
      "change_amount": -4.61,
      "volume": 8176800,
      "close_price": 475.23,
      "after_hours_price": null,
      "after_hours_change_percent": null,
      "after_hours_change_amount": null
    },
    {
      "symbol": "DIVO",
      "price_usd": 45.87,
      "price_type": "close",
      "market_state": "closed",
      "is_delayed": true,
      "stale_level": "fresh",
      "error": null,
      "change_percent": -0.39,
      "change_amount": -0.18,
      "volume": 1466600,
      "close_price": 45.87,
      "after_hours_price": null,
      "after_hours_change_percent": null,
      "after_hours_change_amount": null
    },
    {
      "symbol": "FTNT",
      "price_usd": 83.67,
      "price_type": "close",
      "market_state": "closed",
      "is_delayed": true,
      "stale_level": "fresh",
      "error": null,
      "change_percent": -0.89,
      "change_amount": -0.75,
      "volume": 5656800,
      "close_price": 83.67,
      "after_hours_price": null,
      "after_hours_change_percent": null,
      "after_hours_change_amount": null
    },
    {
      "symbol": "GEV",
      "price_usd": 789.23,
      "price_type": "close",
      "market_state": "closed",
      "is_delayed": true,
      "stale_level": "fresh",
      "error": null,
      "change_percent": -3.16,
      "change_amount": -25.78,
      "volume": 2673800,
      "close_price": 789.23,
      "after_hours_price": null,
      "after_hours_change_percent": null,
      "after_hours_change_amount": null
    },
    {
      "symbol": "GLD",
      "price_usd": 473.51,
      "price_type": "close",
      "market_state": "closed",
      "is_delayed": true,
      "stale_level": "fresh",
      "error": null,
      "change_percent": 1.58,
      "change_amount": 7.38,
      "volume": 10453800,
      "close_price": 473.51,
      "after_hours_price": null,
      "after_hours_change_percent": null,
      "after_hours_change_amount": null
    },
    {
      "symbol": "GLW",
      "price_usd": 123.29,
      "price_type": "close",
      "market_state": "closed",
      "is_delayed": true,
      "stale_level": "fresh",
      "error": null,
      "change_percent": -8.5,
      "change_amount": -11.45,
      "volume": 19094000,
      "close_price": 123.29,
      "after_hours_price": null,
      "after_hours_change_percent": null,
      "after_hours_change_amount": null
    },
    {
      "symbol": "GS",
      "price_usd": 821.42,
      "price_type": "close",
      "market_state": "closed",
      "is_delayed": true,
      "stale_level": "fresh",
      "error": null,
      "change_percent": -1.68,
      "change_amount": -14.04,
      "volume": 2472200,
      "close_price": 821.42,
      "after_hours_price": null,
      "after_hours_change_percent": null,
      "after_hours_change_amount": null
    },
    {
      "symbol": "HD",
      "price_usd": 357.92,
      "price_type": "close",
      "market_state": "closed",
      "is_delayed": true,
      "stale_level": "fresh",
      "error": null,
      "change_percent": -1.04,
      "change_amount": -3.76,
      "volume": 4167400,
      "close_price": 357.92,
      "after_hours_price": null,
      "after_hours_change_percent": null,
      "after_hours_change_amount": null
    },
    {
      "symbol": "HON",
      "price_usd": 235.29,
      "price_type": "close",
      "market_state": "closed",
      "is_delayed": true,
      "stale_level": "fresh",
      "error": null,
      "change_percent": -1.3,
      "change_amount": -3.09,
      "volume": 3856700,
      "close_price": 235.29,
      "after_hours_price": null,
      "after_hours_change_percent": null,
      "after_hours_change_amount": null
    },
    {
      "symbol": "HUT",
      "price_usd": 47.07,
      "price_type": "close",
      "market_state": "closed",
      "is_delayed": true,
      "stale_level": "fresh",
      "error": null,
      "change_percent": -8.35,
      "change_amount": -4.29,
      "volume": 4170500,
      "close_price": 47.07,
      "after_hours_price": null,
      "after_hours_change_percent": null,
      "after_hours_change_amount": null
    },
    {
      "symbol": "IBM",
      "price_usd": 258.85,
      "price_type": "close",
      "market_state": "closed",
      "is_delayed": true,
      "stale_level": "fresh",
      "error": null,
      "change_percent": 0.9,
      "change_amount": 2.3,
      "volume": 6233100,
      "close_price": 258.85,
      "after_hours_price": null,
      "after_hours_change_percent": null,
      "after_hours_change_amount": null
    },
    {
      "symbol": "INTU",
      "price_usd": 481.17,
      "price_type": "close",
      "market_state": "closed",
      "is_delayed": true,
      "stale_level": "fresh",
      "error": null,
      "change_percent": 3.08,
      "change_amount": 14.38,
      "volume": 5502300,
      "close_price": 481.17,
      "after_hours_price": null,
      "after_hours_change_percent": null,
      "after_hours_change_amount": null
    },
    {
      "symbol": "IWM",
      "price_usd": 250.89,
      "price_type": "close",
      "market_state": "closed",
      "is_delayed": true,
      "stale_level": "fresh",
      "error": null,
      "change_percent": -2.29,
      "change_amount": -5.87,
      "volume": 64162800,
      "close_price": 250.89,
      "after_hours_price": null,
      "after_hours_change_percent": null,
      "after_hours_change_amount": null
    },
    {
      "symbol": "JEPI",
      "price_usd": 58.09,
      "price_type": "close",
      "market_state": "closed",
      "is_delayed": true,
      "stale_level": "fresh",
      "error": null,
      "change_percent": -0.9,
      "change_amount": -0.53,
      "volume": 6022900,
      "close_price": 58.09,
      "after_hours_price": null,
      "after_hours_change_percent": null,
      "after_hours_change_amount": null
    },
    {
      "symbol": "JEPQ",
      "price_usd": 56.85,
      "price_type": "close",
      "market_state": "closed",
      "is_delayed": true,
      "stale_level": "fresh",
      "error": null,
      "change_percent": -1.37,
      "change_amount": -0.79,
      "volume": 7488500,
      "close_price": 56.85,
      "after_hours_price": null,
      "after_hours_change_percent": null,
      "after_hours_change_amount": null
    },
    {
      "symbol": "JNJ",
      "price_usd": 240.4,
      "price_type": "close",
      "market_state": "closed",
      "is_delayed": true,
      "stale_level": "fresh",
      "error": null,
      "change_percent": 0.32,
      "change_amount": 0.77,
      "volume": 7178800,
      "close_price": 240.4,
      "after_hours_price": null,
      "after_hours_change_percent": null,
      "after_hours_change_amount": null
    },
    {
      "symbol": "JOBY",
      "price_usd": 9.55,
      "price_type": "close",
      "market_state": "closed",
      "is_delayed": true,
      "stale_level": "fresh",
      "error": null,
      "change_percent": -0.62,
      "change_amount": -0.06,
      "volume": 14815100,
      "close_price": 9.55,
      "after_hours_price": null,
      "after_hours_change_percent": null,
      "after_hours_change_amount": null
    },
    {
      "symbol": "JPM",
      "price_usd": 289.48,
      "price_type": "close",
      "market_state": "closed",
      "is_delayed": true,
      "stale_level": "fresh",
      "error": null,
      "change_percent": -1.39,
      "change_amount": -4.07,
      "volume": 13491200,
      "close_price": 289.48,
      "after_hours_price": null,
      "after_hours_change_percent": null,
      "after_hours_change_amount": null
    },
    {
      "symbol": "KO",
      "price_usd": 77.04,
      "price_type": "close",
      "market_state": "closed",
      "is_delayed": true,
      "stale_level": "fresh",
      "error": null,
      "change_percent": 0.01,
      "change_amount": 0.01,
      "volume": 15511700,
      "close_price": 77.04,
      "after_hours_price": null,
      "after_hours_change_percent": null,
      "after_hours_change_amount": null
    },
    {
      "symbol": "MA",
      "price_usd": 522.34,
      "price_type": "close",
      "market_state": "closed",
      "is_delayed": true,
      "stale_level": "fresh",
      "error": null,
      "change_percent": -0.44,
      "change_amount": -2.32,
      "volume": 2872900,
      "close_price": 522.34,
      "after_hours_price": null,
      "after_hours_change_percent": null,
      "after_hours_change_amount": null
    },
    {
      "symbol": "MAIN",
      "price_usd": 57.37,
      "price_type": "close",
      "market_state": "closed",
      "is_delayed": true,
      "stale_level": "fresh",
      "error": null,
      "change_percent": -1.6,
      "change_amount": -0.93,
      "volume": 414500,
      "close_price": 57.37,
      "after_hours_price": null,
      "after_hours_change_percent": null,
      "after_hours_change_amount": null
    },
    {
      "symbol": "MCD",
      "price_usd": 328.06,
      "price_type": "close",
      "market_state": "closed",
      "is_delayed": true,
      "stale_level": "fresh",
      "error": null,
      "change_percent": 0.19,
      "change_amount": 0.61,
      "volume": 3341200,
      "close_price": 328.06,
      "after_hours_price": null,
      "after_hours_change_percent": null,
      "after_hours_change_amount": null
    },
    {
      "symbol": "MMM",
      "price_usd": 153.41,
      "price_type": "close",
      "market_state": "closed",
      "is_delayed": true,
      "stale_level": "fresh",
      "error": null,
      "change_percent": -1.79,
      "change_amount": -2.8,
      "volume": 4938100,
      "close_price": 153.41,
      "after_hours_price": null,
      "after_hours_change_percent": null,
      "after_hours_change_amount": null
    },
    {
      "symbol": "MRK",
      "price_usd": 115.79,
      "price_type": "close",
      "market_state": "closed",
      "is_delayed": true,
      "stale_level": "fresh",
      "error": null,
      "change_percent": -0.24,
      "change_amount": -0.28,
      "volume": 12808300,
      "close_price": 115.79,
      "after_hours_price": null,
      "after_hours_change_percent": null,
      "after_hours_change_amount": null
    },
    {
      "symbol": "MU",
      "price_usd": 370.3,
      "price_type": "close",
      "market_state": "closed",
      "is_delayed": true,
      "stale_level": "fresh",
      "error": null,
      "change_percent": -6.74,
      "change_amount": -26.75,
      "volume": 34289500,
      "close_price": 370.3,
      "after_hours_price": null,
      "after_hours_change_percent": null,
      "after_hours_change_amount": null
    },
    {
      "symbol": "NET",
      "price_usd": 195.19,
      "price_type": "close",
      "market_state": "closed",
      "is_delayed": true,
      "stale_level": "fresh",
      "error": null,
      "change_percent": 1.5,
      "change_amount": 2.88,
      "volume": 2860300,
      "close_price": 195.19,
      "after_hours_price": null,
      "after_hours_change_percent": null,
      "after_hours_change_amount": null
    },
    {
      "symbol": "O",
      "price_usd": 65,
      "price_type": "close",
      "market_state": "closed",
      "is_delayed": true,
      "stale_level": "fresh",
      "error": null,
      "change_percent": 0.31,
      "change_amount": 0.2,
      "volume": 6235700,
      "close_price": 65,
      "after_hours_price": null,
      "after_hours_change_percent": null,
      "after_hours_change_amount": null
    },
    {
      "symbol": "PG",
      "price_usd": 153.63,
      "price_type": "close",
      "market_state": "closed",
      "is_delayed": true,
      "stale_level": "fresh",
      "error": null,
      "change_percent": -0.23,
      "change_amount": -0.36,
      "volume": 8186500,
      "close_price": 153.63,
      "after_hours_price": null,
      "after_hours_change_percent": null,
      "after_hours_change_amount": null
    },
    {
      "symbol": "PM",
      "price_usd": 169.98,
      "price_type": "close",
      "market_state": "closed",
      "is_delayed": true,
      "stale_level": "fresh",
      "error": null,
      "change_percent": 0.16,
      "change_amount": 0.28,
      "volume": 5070700,
      "close_price": 169.98,
      "after_hours_price": null,
      "after_hours_change_percent": null,
      "after_hours_change_amount": null
    },
    {
      "symbol": "POWL",
      "price_usd": 483.65,
      "price_type": "close",
      "market_state": "closed",
      "is_delayed": true,
      "stale_level": "fresh",
      "error": null,
      "change_percent": -3.85,
      "change_amount": -19.36,
      "volume": 190600,
      "close_price": 483.65,
      "after_hours_price": null,
      "after_hours_change_percent": null,
      "after_hours_change_amount": null
    },
    {
      "symbol": "QBTS",
      "price_usd": 18.59,
      "price_type": "close",
      "market_state": "closed",
      "is_delayed": true,
      "stale_level": "fresh",
      "error": null,
      "change_percent": -1.27,
      "change_amount": -0.24,
      "volume": 27185400,
      "close_price": 18.59,
      "after_hours_price": null,
      "after_hours_change_percent": null,
      "after_hours_change_amount": null
    },
    {
      "symbol": "QQQ",
      "price_usd": 599.75,
      "price_type": "close",
      "market_state": "closed",
      "is_delayed": true,
      "stale_level": "fresh",
      "error": null,
      "change_percent": -1.5,
      "change_amount": -9.16,
      "volume": 86221800,
      "close_price": 599.75,
      "after_hours_price": null,
      "after_hours_change_percent": null,
      "after_hours_change_amount": null
    },
    {
      "symbol": "RGTI",
      "price_usd": 17.01,
      "price_type": "close",
      "market_state": "closed",
      "is_delayed": true,
      "stale_level": "fresh",
      "error": null,
      "change_percent": 0.24,
      "change_amount": 0.04,
      "volume": 26729400,
      "close_price": 17.01,
      "after_hours_price": null,
      "after_hours_change_percent": null,
      "after_hours_change_amount": null
    },
    {
      "symbol": "RTX",
      "price_usd": 209.76,
      "price_type": "close",
      "market_state": "closed",
      "is_delayed": true,
      "stale_level": "fresh",
      "error": null,
      "change_percent": 2.89,
      "change_amount": 5.9,
      "volume": 8758300,
      "close_price": 209.76,
      "after_hours_price": null,
      "after_hours_change_percent": null,
      "after_hours_change_amount": null
    },
    {
      "symbol": "SCHD",
      "price_usd": 31.13,
      "price_type": "close",
      "market_state": "closed",
      "is_delayed": true,
      "stale_level": "fresh",
      "error": null,
      "change_percent": -0.42,
      "change_amount": -0.13,
      "volume": 30677900,
      "close_price": 31.13,
      "after_hours_price": null,
      "after_hours_change_percent": null,
      "after_hours_change_amount": null
    },
    {
      "symbol": "SLV",
      "price_usd": 75.94,
      "price_type": "close",
      "market_state": "closed",
      "is_delayed": true,
      "stale_level": "fresh",
      "error": null,
      "change_percent": 2.25,
      "change_amount": 1.67,
      "volume": 40389300,
      "close_price": 75.94,
      "after_hours_price": null,
      "after_hours_change_percent": null,
      "after_hours_change_amount": null
    },
    {
      "symbol": "SMCI",
      "price_usd": 31.31,
      "price_type": "close",
      "market_state": "closed",
      "is_delayed": true,
      "stale_level": "fresh",
      "error": null,
      "change_percent": -2.88,
      "change_amount": -0.93,
      "volume": 21094600,
      "close_price": 31.31,
      "after_hours_price": null,
      "after_hours_change_percent": null,
      "after_hours_change_amount": null
    },
    {
      "symbol": "SNDK",
      "price_usd": 527.33,
      "price_type": "close",
      "market_state": "closed",
      "is_delayed": true,
      "stale_level": "fresh",
      "error": null,
      "change_percent": -6.76,
      "change_amount": -38.26,
      "volume": 16010500,
      "close_price": 527.33,
      "after_hours_price": null,
      "after_hours_change_percent": null,
      "after_hours_change_amount": null
    },
    {
      "symbol": "SPY",
      "price_usd": 672.38,
      "price_type": "close",
      "market_state": "closed",
      "is_delayed": true,
      "stale_level": "fresh",
      "error": null,
      "change_percent": -1.31,
      "change_amount": -8.93,
      "volume": 100509800,
      "close_price": 672.38,
      "after_hours_price": null,
      "after_hours_change_percent": null,
      "after_hours_change_amount": null
    },
    {
      "symbol": "TRV",
      "price_usd": 306.31,
      "price_type": "close",
      "market_state": "closed",
      "is_delayed": true,
      "stale_level": "fresh",
      "error": null,
      "change_percent": -0.11,
      "change_amount": -0.33,
      "volume": 1268500,
      "close_price": 306.31,
      "after_hours_price": null,
      "after_hours_change_percent": null,
      "after_hours_change_amount": null
    },
    {
      "symbol": "UNG",
      "price_usd": 12.75,
      "price_type": "close",
      "market_state": "closed",
      "is_delayed": true,
      "stale_level": "fresh",
      "error": null,
      "change_percent": 5.81,
      "change_amount": 0.7,
      "volume": 26276700,
      "close_price": 12.75,
      "after_hours_price": null,
      "after_hours_change_percent": null,
      "after_hours_change_amount": null
    },
    {
      "symbol": "UNH",
      "price_usd": 286.48,
      "price_type": "close",
      "market_state": "closed",
      "is_delayed": true,
      "stale_level": "fresh",
      "error": null,
      "change_percent": -0.79,
      "change_amount": -2.29,
      "volume": 6810100,
      "close_price": 286.48,
      "after_hours_price": null,
      "after_hours_change_percent": null,
      "after_hours_change_amount": null
    },
    {
      "symbol": "USO",
      "price_usd": 108.77,
      "price_type": "close",
      "market_state": "closed",
      "is_delayed": true,
      "stale_level": "fresh",
      "error": null,
      "change_percent": 12.94,
      "change_amount": 12.46,
      "volume": 68296600,
      "close_price": 108.77,
      "after_hours_price": null,
      "after_hours_change_percent": null,
      "after_hours_change_amount": null
    },
    {
      "symbol": "V",
      "price_usd": 317.36,
      "price_type": "close",
      "market_state": "closed",
      "is_delayed": true,
      "stale_level": "fresh",
      "error": null,
      "change_percent": -0.76,
      "change_amount": -2.44,
      "volume": 6438700,
      "close_price": 317.36,
      "after_hours_price": null,
      "after_hours_change_percent": null,
      "after_hours_change_amount": null
    },
    {
      "symbol": "VIG",
      "price_usd": 221.52,
      "price_type": "close",
      "market_state": "closed",
      "is_delayed": true,
      "stale_level": "fresh",
      "error": null,
      "change_percent": -0.86,
      "change_amount": -1.93,
      "volume": 1591300,
      "close_price": 221.52,
      "after_hours_price": null,
      "after_hours_change_percent": null,
      "after_hours_change_amount": null
    },
    {
      "symbol": "VNQ",
      "price_usd": 93.55,
      "price_type": "close",
      "market_state": "closed",
      "is_delayed": true,
      "stale_level": "fresh",
      "error": null,
      "change_percent": -1.09,
      "change_amount": -1.03,
      "volume": 4605500,
      "close_price": 93.55,
      "after_hours_price": null,
      "after_hours_change_percent": null,
      "after_hours_change_amount": null
    },
    {
      "symbol": "VTV",
      "price_usd": 200.03,
      "price_type": "close",
      "market_state": "closed",
      "is_delayed": true,
      "stale_level": "fresh",
      "error": null,
      "change_percent": -1.14,
      "change_amount": -2.3,
      "volume": 7044800,
      "close_price": 200.03,
      "after_hours_price": null,
      "after_hours_change_percent": null,
      "after_hours_change_amount": null
    },
    {
      "symbol": "VUG",
      "price_usd": 458.08,
      "price_type": "close",
      "market_state": "closed",
      "is_delayed": true,
      "stale_level": "fresh",
      "error": null,
      "change_percent": -1.34,
      "change_amount": -6.23,
      "volume": 1723100,
      "close_price": 458.08,
      "after_hours_price": null,
      "after_hours_change_percent": null,
      "after_hours_change_amount": null
    },
    {
      "symbol": "VYM",
      "price_usd": 150.74,
      "price_type": "close",
      "market_state": "closed",
      "is_delayed": true,
      "stale_level": "fresh",
      "error": null,
      "change_percent": -0.87,
      "change_amount": -1.33,
      "volume": 1887200,
      "close_price": 150.74,
      "after_hours_price": null,
      "after_hours_change_percent": null,
      "after_hours_change_amount": null
    },
    {
      "symbol": "WDC",
      "price_usd": 245.25,
      "price_type": "close",
      "market_state": "closed",
      "is_delayed": true,
      "stale_level": "fresh",
      "error": null,
      "change_percent": -5.32,
      "change_amount": -13.78,
      "volume": 6336300,
      "close_price": 245.25,
      "after_hours_price": null,
      "after_hours_change_percent": null,
      "after_hours_change_amount": null
    },
    {
      "symbol": "WFC",
      "price_usd": 80.42,
      "price_type": "close",
      "market_state": "closed",
      "is_delayed": true,
      "stale_level": "fresh",
      "error": null,
      "change_percent": -2.06,
      "change_amount": -1.69,
      "volume": 16798400,
      "close_price": 80.42,
      "after_hours_price": null,
      "after_hours_change_percent": null,
      "after_hours_change_amount": null
    },
    {
      "symbol": "WMT",
      "price_usd": 123.8,
      "price_type": "close",
      "market_state": "closed",
      "is_delayed": true,
      "stale_level": "fresh",
      "error": null,
      "change_percent": 0.4,
      "change_amount": 0.49,
      "volume": 21548500,
      "close_price": 123.8,
      "after_hours_price": null,
      "after_hours_change_percent": null,
      "after_hours_change_amount": null
    },
    {
      "symbol": "WULF",
      "price_usd": 13.75,
      "price_type": "close",
      "market_state": "closed",
      "is_delayed": true,
      "stale_level": "fresh",
      "error": null,
      "change_percent": -9.72,
      "change_amount": -1.48,
      "volume": 32592300,
      "close_price": 13.75,
      "after_hours_price": null,
      "after_hours_change_percent": null,
      "after_hours_change_amount": null
    },
    {
      "symbol": "XOM",
      "price_usd": 151.21,
      "price_type": "close",
      "market_state": "closed",
      "is_delayed": true,
      "stale_level": "fresh",
      "error": null,
      "change_percent": 0.3,
      "change_amount": 0.45,
      "volume": 21105800,
      "close_price": 151.21,
      "after_hours_price": null,
      "after_hours_change_percent": null,
      "after_hours_change_amount": null
    },
    {
      "symbol": "ZS",
      "price_usd": 164.06,
      "price_type": "close",
      "market_state": "closed",
      "is_delayed": true,
      "stale_level": "fresh",
      "error": null,
      "change_percent": 1.3,
      "change_amount": 2.1,
      "volume": 2531400,
      "close_price": 164.06,
      "after_hours_price": null,
      "after_hours_change_percent": null,
      "after_hours_change_amount": null
    }
  ],
  "metadata": {
    "total_symbols": 137,
    "successful_updates": 137,
    "failed_updates": 0,
    "average_delay_minutes": 15,
    "next_update": "2026-03-08T08:17:02.477Z"
  }
}