{
  "defaultKeyStatistics": {
    "maxAge": 1,
    "priceHint": 2,
    "category": "Commodities Focused",
    "ytdReturn": 0.0759506,
    "beta3Year": 0.67,
    "totalAssets": 184864325632,
    "yield": 0,
    "fundFamily": "State Street Investment Management",
    "fundInceptionDate": "2004-11-18T00:00:00.000Z",
    "legalType": "Exchange Traded Fund",
    "threeYearAverageReturn": 0.323887,
    "fiveYearAverageReturn": 0.21171409,
    "lastSplitFactor": null,
    "latestShareClass": null,
    "leadInvestor": null
  },
  "summaryProfile": {
    "longBusinessSummary": "The Trust holds gold bars and from time to time, issues Baskets in exchange for deposits of gold and distributes gold in connection with redemptions of Baskets. The investment objective of the Trust is for the Shares to reflect the performance of the price of gold bullion, less the Trust’s expenses. The Sponsor believes that, for many investors, the Shares represent a cost-effective investment in gold.",
    "companyOfficers": [],
    "executiveTeam": [],
    "maxAge": 86400
  },
  "price": {
    "maxAge": 1,
    "preMarketSource": "FREE_REALTIME",
    "postMarketChangePercent": -0.00154559,
    "postMarketChange": -0.638916,
    "postMarketTime": "2026-03-20T23:59:56.000Z",
    "postMarketPrice": 412.7411,
    "postMarketSource": "FREE_REALTIME",
    "regularMarketChangePercent": -0.030557401,
    "regularMarketChange": -13.03,
    "regularMarketTime": "2026-03-20T20:00:00.000Z",
    "priceHint": 2,
    "regularMarketPrice": 413.38,
    "regularMarketDayHigh": 428.59,
    "regularMarketDayLow": 411.27,
    "regularMarketVolume": 26108743,
    "averageDailyVolume10Day": 14189470,
    "averageDailyVolume3Month": 18577673,
    "regularMarketPreviousClose": 426.41,
    "regularMarketSource": "FREE_REALTIME",
    "regularMarketOpen": 428.09,
    "exchange": "PCX",
    "exchangeName": "NYSEArca",
    "exchangeDataDelayedBy": 0,
    "marketState": "CLOSED",
    "quoteType": "ETF",
    "symbol": "GLD",
    "underlyingSymbol": null,
    "shortName": "SPDR Gold Shares",
    "longName": "SPDR Gold Shares",
    "currency": "USD",
    "quoteSourceName": "Nasdaq Real Time Price",
    "currencySymbol": "$",
    "fromCurrency": null,
    "toCurrency": null,
    "lastMarket": null,
    "marketCap": 107602812928
  },
  "lastUpdated": "2026-03-21T04:09:02.526Z",
  "source": "Static Build (yahoo-finance2)"
}