{
  "defaultKeyStatistics": {
    "maxAge": 1,
    "priceHint": 2,
    "category": "Large Growth",
    "ytdReturn": -0.0207224,
    "beta3Year": 1.12,
    "totalAssets": 411780087808,
    "yield": 0.0045,
    "fundFamily": "Invesco",
    "fundInceptionDate": "1999-03-10T00:00:00.000Z",
    "legalType": "Exchange Traded Fund",
    "threeYearAverageReturn": 0.26898968,
    "fiveYearAverageReturn": 0.1492735,
    "lastSplitFactor": null,
    "latestShareClass": null,
    "leadInvestor": null
  },
  "summaryProfile": {
    "longBusinessSummary": "To maintain the correspondence between the composition and weights of the securities in the trust (the \"securities\") and the stocks in the NASDAQ-100 Index®, the adviser adjusts the securities from time to time to conform to periodic changes in the identity and/or relative weights of index securities. The composition and weighting of the securities portion of a portfolio deposit are also adjusted to conform to changes in the index.",
    "companyOfficers": [],
    "executiveTeam": [],
    "maxAge": 86400
  },
  "price": {
    "maxAge": 1,
    "preMarketSource": "FREE_REALTIME",
    "postMarketChangePercent": 0.0032195982,
    "postMarketChange": 1.9663696,
    "postMarketTime": "2026-03-05T01:00:00.000Z",
    "postMarketPrice": 612.7164,
    "postMarketSource": "FREE_REALTIME",
    "regularMarketChangePercent": 0.0152432,
    "regularMarketChange": 9.16998,
    "regularMarketTime": "2026-03-04T21:00:01.000Z",
    "priceHint": 2,
    "regularMarketPrice": 610.75,
    "regularMarketDayHigh": 612.88,
    "regularMarketDayLow": 603.43,
    "regularMarketVolume": 69315779,
    "averageDailyVolume10Day": 71051650,
    "averageDailyVolume3Month": 58354805,
    "regularMarketPreviousClose": 601.58,
    "regularMarketSource": "FREE_REALTIME",
    "regularMarketOpen": 604.15,
    "exchange": "NGM",
    "exchangeName": "NasdaqGM",
    "exchangeDataDelayedBy": 0,
    "marketState": "POSTPOST",
    "quoteType": "ETF",
    "symbol": "QQQ",
    "underlyingSymbol": null,
    "shortName": "Invesco QQQ Trust, Series 1",
    "longName": "Invesco QQQ Trust",
    "currency": "USD",
    "quoteSourceName": "Nasdaq Real Time Price",
    "currencySymbol": "$",
    "fromCurrency": null,
    "toCurrency": null,
    "lastMarket": null,
    "marketCap": 240085827584
  },
  "lastUpdated": "2026-03-05T04:16:35.956Z",
  "source": "Static Build (yahoo-finance2)"
}