{
  "defaultKeyStatistics": {
    "maxAge": 1,
    "priceHint": 2,
    "category": "Commodities Focused",
    "ytdReturn": 0.2291214,
    "beta3Year": 2.08,
    "totalAssets": 51481948160,
    "yield": 0,
    "fundFamily": "iShares",
    "fundInceptionDate": "2006-04-21T00:00:00.000Z",
    "legalType": "Exchange Traded Fund",
    "threeYearAverageReturn": 0.5672095,
    "fiveYearAverageReturn": 0.26462218,
    "lastSplitFactor": null,
    "latestShareClass": null,
    "leadInvestor": null
  },
  "summaryProfile": {
    "longBusinessSummary": "The Trust seeks to reflect such performance before payment of the Trust's expenses and liabilities. It is not actively managed. The Trust does not engage in any activities designed to obtain a profit from, or to ameliorate losses caused by, changes in the price of silver.",
    "companyOfficers": [],
    "executiveTeam": [],
    "maxAge": 86400
  },
  "price": {
    "maxAge": 1,
    "preMarketSource": "FREE_REALTIME",
    "postMarketChangePercent": -0.046345796,
    "postMarketChange": -3.0908012,
    "postMarketTime": "2026-02-06T01:00:00.000Z",
    "postMarketPrice": 63.5992,
    "postMarketSource": "FREE_REALTIME",
    "regularMarketChangePercent": -0.15774201,
    "regularMarketChange": -12.49,
    "regularMarketTime": "2026-02-05T21:00:00.000Z",
    "priceHint": 2,
    "regularMarketPrice": 66.69,
    "regularMarketDayHigh": 70.52,
    "regularMarketDayLow": 65.51,
    "regularMarketVolume": 152009213,
    "averageDailyVolume10Day": 230720690,
    "averageDailyVolume3Month": 94912743,
    "regularMarketPreviousClose": 79.18,
    "regularMarketSource": "FREE_REALTIME",
    "regularMarketOpen": 68.23,
    "exchange": "PCX",
    "exchangeName": "NYSEArca",
    "exchangeDataDelayedBy": 0,
    "marketState": "PREPRE",
    "quoteType": "ETF",
    "symbol": "SLV",
    "underlyingSymbol": null,
    "shortName": "iShares Silver Trust",
    "longName": "iShares Silver Trust",
    "currency": "USD",
    "quoteSourceName": "Nasdaq Real Time Price",
    "currencySymbol": "$",
    "fromCurrency": null,
    "toCurrency": null,
    "lastMarket": null,
    "marketCap": 22771300352
  },
  "lastUpdated": "2026-02-06T06:51:12.211Z",
  "source": "Static Build (yahoo-finance2)"
}