{
  "defaultKeyStatistics": {
    "maxAge": 1,
    "priceHint": 2,
    "category": "Large Blend",
    "ytdReturn": 0.0176414,
    "beta3Year": 1,
    "totalAssets": 708919230464,
    "yield": 0.0105,
    "fundFamily": "State Street Investment Management",
    "fundInceptionDate": "1993-01-22T00:00:00.000Z",
    "legalType": "Exchange Traded Fund",
    "threeYearAverageReturn": 0.2104332,
    "fiveYearAverageReturn": 0.13761911,
    "lastSplitFactor": null,
    "latestShareClass": null,
    "leadInvestor": null
  },
  "summaryProfile": {
    "longBusinessSummary": "The trust seeks to achieve its investment objective by holding a portfolio of the common stocks that are included in the index (the “Portfolio”), with the weight of each stock in the Portfolio substantially corresponding to the weight of such stock in the index.",
    "companyOfficers": [],
    "executiveTeam": [],
    "maxAge": 86400
  },
  "price": {
    "maxAge": 1,
    "preMarketSource": "FREE_REALTIME",
    "postMarketChangePercent": 0.0022684033,
    "postMarketChange": 1.5700073,
    "postMarketTime": "2026-02-11T00:59:55.000Z",
    "postMarketPrice": 693.69,
    "postMarketSource": "DELAYED",
    "regularMarketChangePercent": -0.0026371,
    "regularMarketChange": -1.83002,
    "regularMarketTime": "2026-02-10T21:00:04.000Z",
    "priceHint": 2,
    "regularMarketPrice": 692.12,
    "regularMarketDayHigh": 696.54,
    "regularMarketDayLow": 691.66,
    "regularMarketVolume": 64974896,
    "averageDailyVolume10Day": 88501890,
    "averageDailyVolume3Month": 82664095,
    "regularMarketPreviousClose": 693.95,
    "regularMarketSource": "FREE_REALTIME",
    "regularMarketOpen": 694.95,
    "exchange": "PCX",
    "exchangeName": "NYSEArca",
    "exchangeDataDelayedBy": 0,
    "marketState": "POSTPOST",
    "quoteType": "ETF",
    "symbol": "SPY",
    "underlyingSymbol": null,
    "shortName": "State Street SPDR S&P 500 ETF T",
    "longName": "State Street SPDR S&P 500 ETF Trust",
    "currency": "USD",
    "quoteSourceName": "Delayed Quote",
    "currencySymbol": "$",
    "fromCurrency": null,
    "toCurrency": null,
    "lastMarket": null,
    "marketCap": 635215282176
  },
  "lastUpdated": "2026-02-11T04:34:35.973Z",
  "source": "Static Build (yahoo-finance2)"
}