{
  "defaultKeyStatistics": {
    "maxAge": 1,
    "priceHint": 2,
    "category": "Large Value",
    "ytdReturn": 0.081993796,
    "beta3Year": 0.8,
    "totalAssets": 227377659904,
    "yield": 0.0196,
    "fundFamily": "Vanguard",
    "fundInceptionDate": "2000-11-13T00:00:00.000Z",
    "legalType": "Exchange Traded Fund",
    "threeYearAverageReturn": 0.1650711,
    "fiveYearAverageReturn": 0.13152009,
    "lastSplitFactor": null,
    "latestShareClass": null,
    "leadInvestor": null
  },
  "summaryProfile": {
    "phone": "800-523-1036",
    "longBusinessSummary": "The manager employs an indexing investment approach designed to track the performance of the index, a broadly diversified index predominantly made up of value stocks of large U.S. companies. The manager attempts to replicate the target index by investing all, or substantially all, of its assets in the stocks that make up the index, holding each stock in approximately the same proportion as its weighting in the index.",
    "companyOfficers": [],
    "executiveTeam": [],
    "maxAge": 86400
  },
  "price": {
    "maxAge": 1,
    "preMarketSource": "FREE_REALTIME",
    "postMarketChangePercent": -0.0056057046,
    "postMarketChange": -1.1599884,
    "postMarketTime": "2026-02-27T00:59:55.000Z",
    "postMarketPrice": 205.77,
    "postMarketSource": "DELAYED",
    "regularMarketChangePercent": 0.0013549399,
    "regularMarketChange": 0.279999,
    "regularMarketTime": "2026-02-26T21:00:00.000Z",
    "priceHint": 2,
    "regularMarketPrice": 206.93,
    "regularMarketDayHigh": 207.76,
    "regularMarketDayLow": 205.865,
    "regularMarketVolume": 4133550,
    "averageDailyVolume10Day": 4567970,
    "averageDailyVolume3Month": 3978626,
    "regularMarketPreviousClose": 206.65,
    "regularMarketSource": "FREE_REALTIME",
    "regularMarketOpen": 206.74,
    "exchange": "PCX",
    "exchangeName": "NYSEArca",
    "exchangeDataDelayedBy": 0,
    "marketState": "POSTPOST",
    "quoteType": "ETF",
    "symbol": "VTV",
    "underlyingSymbol": null,
    "shortName": "Vanguard Value ETF",
    "longName": "Vanguard Value Index Fund ETF Shares",
    "currency": "USD",
    "quoteSourceName": "Delayed Quote",
    "currencySymbol": "$",
    "fromCurrency": null,
    "toCurrency": null,
    "lastMarket": null,
    "marketCap": 87790256128
  },
  "lastUpdated": "2026-02-27T04:17:38.204Z",
  "source": "Static Build (yahoo-finance2)"
}