{
  "defaultKeyStatistics": {
    "maxAge": 1,
    "priceHint": 2,
    "category": "Large Value",
    "ytdReturn": 0.0969831,
    "beta3Year": 0.77,
    "totalAssets": 88722817024,
    "yield": 0.023699999,
    "fundFamily": "Vanguard",
    "fundInceptionDate": "2006-11-10T00:00:00.000Z",
    "legalType": "Exchange Traded Fund",
    "threeYearAverageReturn": 0.1687764,
    "fiveYearAverageReturn": 0.118171,
    "lastSplitFactor": null,
    "latestShareClass": null,
    "leadInvestor": null
  },
  "summaryProfile": {
    "longBusinessSummary": "The fund employs an indexing investment approach designed to track the performance of the the Target Index, which consists of common stocks of companies that pay dividends that generally are higher than average (excluding real estate investment trusts (“REITs”)). Under normal circumstances, it invests at least 80% of its net assets, plus the amount of any borrowings for investment purposes, in the stocks that make up the Target Index.",
    "companyOfficers": [],
    "executiveTeam": [],
    "maxAge": 86400
  },
  "price": {
    "maxAge": 1,
    "preMarketSource": "FREE_REALTIME",
    "postMarketChangePercent": 0.0010861809,
    "postMarketChange": 0.16999817,
    "postMarketTime": "2026-05-01T23:59:32.000Z",
    "postMarketPrice": 156.68,
    "postMarketSource": "FREE_REALTIME",
    "regularMarketChangePercent": -0.00432603,
    "regularMarketChange": -0.680008,
    "regularMarketTime": "2026-05-01T20:00:00.000Z",
    "priceHint": 2,
    "regularMarketPrice": 156.51,
    "regularMarketDayHigh": 157.4791,
    "regularMarketDayLow": 156.47,
    "regularMarketVolume": 1164602,
    "averageDailyVolume10Day": 1001020,
    "averageDailyVolume3Month": 1579059,
    "regularMarketPreviousClose": 157.19,
    "regularMarketSource": "FREE_REALTIME",
    "regularMarketOpen": 157.37,
    "exchange": "PCX",
    "exchangeName": "NYSEArca",
    "exchangeDataDelayedBy": 0,
    "marketState": "CLOSED",
    "quoteType": "ETF",
    "symbol": "VYM",
    "underlyingSymbol": null,
    "shortName": "Vanguard High Dividend Yield ET",
    "longName": "Vanguard High Dividend Yield Index Fund ETF Shares",
    "currency": "USD",
    "quoteSourceName": "Nasdaq Real Time Price",
    "currencySymbol": "$",
    "fromCurrency": null,
    "toCurrency": null,
    "lastMarket": null
  },
  "lastUpdated": "2026-05-03T05:33:17.186Z",
  "source": "Static Build (yahoo-finance2)"
}